twinly/__init__.py
twinly/attributes.py
twinly/import_helper.py
twinly/registry.py
twinly/twinly.py
twinly/types.py
twinly/utils.py
twinly/inspectors/__init__.py
twinly/inspectors/base.py
twinly/inspectors/dataclass.py
twinly/inspectors/empty.py
twinly/inspectors/model.py
twinly-0.1.13.dist-info/METADATA
twinly-0.1.13.dist-info/WHEEL
twinly-0.1.13.dist-info/licenses/LICENSE
twinly-0.1.13.dist-info/RECORD
